the_forest_palette/__init__.py
the_forest_palette/palette.py
the_forest_palette-1.0.1.dist-info/METADATA
the_forest_palette-1.0.1.dist-info/WHEEL
the_forest_palette-1.0.1.dist-info/top_level.txt
the_forest_palette-1.0.1.dist-info/RECORD
