Metadata-Version: 2.1
Name: the-forest-palette
Version: 1.0.1
Summary: A package for custom matplotlib color palettes
Author: Beth O'Dwyer
Author-email: Beth O'Dwyer <odwyerbeth621@gmail.com>
Project-URL: Homepage, https://github.com/elodwyer1/the-forest-palette/
Project-URL: Issues, https://github.com/elodwyer1/the-forest-palette/issues
Classifier: Programming Language :: Python :: 3
Classifier: License :: OSI Approved :: MIT License
Classifier: Operating System :: OS Independent
Requires-Python: >=3.6
